LICENSE
README.md
setup.py
RXL/Errors.py
RXL/Grammar.py
RXL/Lib.py
RXL/RXL.py
RXL/__init__.py
RXL/lib.py
RXL.egg-info/PKG-INFO
RXL.egg-info/SOURCES.txt
RXL.egg-info/dependency_links.txt
RXL.egg-info/entry_points.txt
RXL.egg-info/top_level.txt
tests/test.py