Metadata-Version: 2.1
Name: RXL
Version: 0.0.3
Summary: RXL Features
Home-page: https://github.com/Ramin-RX7/RX-Language/
Author: Ramin RX7
Author-email: rawmin.rx@gmail.com
License: LGPL
Classifier: Programming Language :: Python :: 3
Requires-Python: >= 3.8
License-File: LICENSE
